pmd_lib/__init__.py
pmd_lib/core.py
pmd_lib/elements/__init__.py
pmd_lib/elements/common.py
pmd_lib/utils/__init__.py
pmd_lib-0.0.2.dist-info/LICENCE
pmd_lib-0.0.2.dist-info/METADATA
pmd_lib-0.0.2.dist-info/WHEEL
pmd_lib-0.0.2.dist-info/top_level.txt
pmd_lib-0.0.2.dist-info/RECORD
