Metadata-Version: 2.1
Name: pmd-lib
Version: 0.0.2
Summary: A library to simplify creating markdown documents.
Author-email: frameworker <frameworker2@gmail.com>
Project-URL: Homepage, https://gitlab.com/frameworker/python-markdown-library
Project-URL: Bug Tracker, https://gitlab.com/frameworker/python-markdown-library/-/issues
Classifier: Programming Language :: Python :: 3
Classifier: License :: OSI Approved :: MIT License
Classifier: Operating System :: OS Independent
Requires-Python: >=3.11
License-File: LICENCE
